{
  "posts": [
    {
      "postId": 2,
      "title": "두번째",
      "content": "게시글 입니당",
      "likes": 0,
      "views": 3,
      "commentsCnt": 0,
      "date": "2024-11-20 10:42:44",
      "imageUrl": null,
      "author": {
        "userId": 2,
        "nickname": "ahn",
        "profileImg": "http://localhost:2000/images/profile1732066910084.png"
      }
    },
    {
      "postId": 1,
      "title": "첫번째",
      "content": "게시글입니다",
      "likes": 0,
      "views": 1,
      "commentsCnt": 0,
      "date": "2024-11-20 10:42:14",
      "imageUrl": "http://localhost:2000/images/profile1732066934641.png",
      "author": {
        "userId": 1,
        "nickname": "sunday",
        "profileImg": "http://localhost:2000/images/profile1732066882307.png"
      }
    }
  ]
}